runsteps/__init__.py
runsteps-0.5.0.dist-info/LICENSE
runsteps-0.5.0.dist-info/METADATA
runsteps-0.5.0.dist-info/WHEEL
runsteps-0.5.0.dist-info/entry_points.txt
runsteps-0.5.0.dist-info/top_level.txt
runsteps-0.5.0.dist-info/zip-safe
runsteps-0.5.0.dist-info/RECORD
