Metadata-Version: 2.1
Name: runsteps
Version: 0.5.0
Summary: A tool for executing a set of ordered instructions
Home-page: https://github.com/jhuntwork/runsteps
Author: Jeremy Huntwork
Author-email: jhuntwork@lightcubesolutions.com
License: MIT
Keywords: scripting automation
Platform: UNKNOWN
Classifier: Development Status :: 3 - Alpha
Classifier: Intended Audience :: Developers
Classifier: Intended Audience :: Information Technology
Classifier: Intended Audience :: System Administrators
Classifier: Topic :: Utilities
Classifier: License :: OSI Approved :: MIT License
Classifier: Programming Language :: Python :: 3
Classifier: Programming Language :: Python :: 3.6
Classifier: Programming Language :: Python :: 3.7
